{
    "original": [
        {
            "start": "0",
            "dur": "4.14",
            "text": "just when you think things can't get any"
        },
        {
            "start": "1.65",
            "dur": "3.689",
            "text": "stupider they do on Sunday President"
        },
        {
            "start": "4.14",
            "dur": "2.639",
            "text": "Trump tweeted out a gif of himself"
        },
        {
            "start": "5.339",
            "dur": "2.881",
            "text": "clotheslining someone knocked me into"
        },
        {
            "start": "6.779",
            "dur": "3.78",
            "text": "the ground then pummeling him at an old"
        },
        {
            "start": "8.22",
            "dur": "3.51",
            "text": "WWE event in the gift the head of"
        },
        {
            "start": "10.559",
            "dur": "3",
            "text": "Trump's victim has been replaced with"
        },
        {
            "start": "11.73",
            "dur": "3.15",
            "text": "the CNN logo so Trump appears to be"
        },
        {
            "start": "13.559",
            "dur": "3.001",
            "text": "tackling then beating the hell out of"
        },
        {
            "start": "14.88",
            "dur": "4.14",
            "text": "the network in most despises the one"
        },
        {
            "start": "16.56",
            "dur": "4.139",
            "text": "he's used as a foil in his rise to power"
        },
        {
            "start": "19.02",
            "dur": "2.94",
            "text": "Trump CNN tweet followed on the heels of"
        },
        {
            "start": "20.699",
            "dur": "3.451",
            "text": "his tweets from last week in which he"
        },
        {
            "start": "21.96",
            "dur": "3.45",
            "text": "attacked MSNBC's Mika Brzezinski and Joe"
        },
        {
            "start": "24.15",
            "dur": "2.879",
            "text": "Scarborough in the most personal terms"
        },
        {
            "start": "25.41",
            "dur": "3.3",
            "text": "Trump supporters responded with"
        },
        {
            "start": "27.029",
            "dur": "3.391",
            "text": "unrestrained leads much of this Trump"
        },
        {
            "start": "28.71",
            "dur": "3.33",
            "text": "was fighting back CNN meanwhile"
        },
        {
            "start": "30.42",
            "dur": "3.6",
            "text": "responded with the typical restraint and"
        },
        {
            "start": "32.04",
            "dur": "3.24",
            "text": "objectivity reporter after Reporter"
        },
        {
            "start": "34.02",
            "dur": "3.42",
            "text": "declared the Trump's we didn't merely"
        },
        {
            "start": "35.28",
            "dur": "3.869",
            "text": "represent an obvious breach of decency"
        },
        {
            "start": "37.44",
            "dur": "3.689",
            "text": "and unpresidential and apparently"
        },
        {
            "start": "39.149",
            "dur": "4.051",
            "text": "pathological outburst of spontaneous"
        },
        {
            "start": "41.129",
            "dur": "3.93",
            "text": "rage tweeting it promoted violence and"
        },
        {
            "start": "43.2",
            "dur": "3.51",
            "text": "Trump would have blood on his hands if"
        },
        {
            "start": "45.059",
            "dur": "3.421",
            "text": "some rogue follower picked up a gun and"
        },
        {
            "start": "46.71",
            "dur": "3.57",
            "text": "decided to come after brian Stelter"
        },
        {
            "start": "48.48",
            "dur": "3.809",
            "text": "Trump supporters responded to this"
        },
        {
            "start": "50.28",
            "dur": "3.509",
            "text": "outpouring of faux rage by CNN by"
        },
        {
            "start": "52.289",
            "dur": "2.731",
            "text": "shouting about Kathy Griffin carrying"
        },
        {
            "start": "53.789",
            "dur": "3.511",
            "text": "around a bloodied mop head of Trump"
        },
        {
            "start": "55.02",
            "dur": "2.67",
            "text": "Julius Caesar presented by Shakespeare"
        },
        {
            "start": "57.3",
            "dur": "2.189",
            "text": "in the Park"
        },
        {
            "start": "57.69",
            "dur": "3.45",
            "text": "as an assassination of Trump and"
        },
        {
            "start": "59.489",
            "dur": "3.09",
            "text": "Democrats from coast to coast to"
        },
        {
            "start": "61.14",
            "dur": "3.089",
            "text": "proclaim that Trump care would end with"
        },
        {
            "start": "62.579",
            "dur": "3.811",
            "text": "grandma being shoved off a cliff by"
        },
        {
            "start": "64.229",
            "dur": "3.721",
            "text": "Speaker of the House Paul Ryan in this"
        },
        {
            "start": "66.39",
            "dur": "3.18",
            "text": "Kabuki theater both sides are right in"
        },
        {
            "start": "67.95",
            "dur": "3.33",
            "text": "both sides are wrong the media are right"
        },
        {
            "start": "69.57",
            "dur": "3.119",
            "text": "the president is acting out in a fashion"
        },
        {
            "start": "71.28",
            "dur": "3.42",
            "text": "that makes my three-year-olds temper"
        },
        {
            "start": "72.689",
            "dur": "3.481",
            "text": "tantrum seem mature by comparison Trump"
        },
        {
            "start": "74.7",
            "dur": "3",
            "text": "supporters are right that the media's"
        },
        {
            "start": "76.17",
            "dur": "2.07",
            "text": "coverage is so wildly corrupt and"
        },
        {
            "start": "77.7",
            "dur": "2.07",
            "text": "hysterical"
        },
        {
            "start": "78.24",
            "dur": "3.51",
            "text": "it makes Leo bloom and the producers"
        },
        {
            "start": "79.77",
            "dur": "3.57",
            "text": "look like Mother Teresa the media are"
        },
        {
            "start": "81.75",
            "dur": "3.24",
            "text": "wrong that their liberties are some sort"
        },
        {
            "start": "83.34",
            "dur": "3.12",
            "text": "of existential assault from the"
        },
        {
            "start": "84.99",
            "dur": "2.85",
            "text": "president who's merely mouthing off the"
        },
        {
            "start": "86.46",
            "dur": "3.03",
            "text": "way he has this entire career"
        },
        {
            "start": "87.84",
            "dur": "3.3",
            "text": "Trump supporters are wrong that all"
        },
        {
            "start": "89.49",
            "dur": "3.269",
            "text": "evils can be excused by simply pointing"
        },
        {
            "start": "91.14",
            "dur": "3.39",
            "text": "at the latest media bad actor and"
        },
        {
            "start": "92.759",
            "dur": "4.711",
            "text": "yelling war are at the top of your lungs"
        },
        {
            "start": "94.53",
            "dur": "4.47",
            "text": "so here we are a media nobody trusts"
        },
        {
            "start": "97.47",
            "dur": "3.6",
            "text": "school harming a president who's the"
        },
        {
            "start": "99",
            "dur": "3.75",
            "text": "class clown nobody looks really good in"
        },
        {
            "start": "101.07",
            "dur": "3.36",
            "text": "this particular fake wrestling match the"
        },
        {
            "start": "102.75",
            "dur": "3.57",
            "text": "question is actually why anyone engages"
        },
        {
            "start": "104.43",
            "dur": "3.99",
            "text": "in it at all after all we know the match"
        },
        {
            "start": "106.32",
            "dur": "3.509",
            "text": "isn't real from so adores media"
        },
        {
            "start": "108.42",
            "dur": "2.879",
            "text": "attention that of CNN and the New York"
        },
        {
            "start": "109.829",
            "dur": "2.701",
            "text": "Times were to stop covering him he"
        },
        {
            "start": "111.299",
            "dur": "3.241",
            "text": "quickly set himself on fire outside"
        },
        {
            "start": "112.53",
            "dur": "3.78",
            "text": "their studios for the cameras likewise"
        },
        {
            "start": "114.54",
            "dur": "3.119",
            "text": "if Trump were to stop tweeting CNN would"
        },
        {
            "start": "116.31",
            "dur": "3.39",
            "text": "have to go back to covering missing"
        },
        {
            "start": "117.659",
            "dur": "3.99",
            "text": "Malaysian airliner it's a romance made"
        },
        {
            "start": "119.7",
            "dur": "4.019",
            "text": "in hell but the ratings are absolutely"
        },
        {
            "start": "121.649",
            "dur": "4.021",
            "text": "stellar so the question remains why does"
        },
        {
            "start": "123.719",
            "dur": "3.121",
            "text": "everyone treat this game as if it's"
        },
        {
            "start": "125.67",
            "dur": "3.229",
            "text": "being played for high stakes"
        },
        {
            "start": "126.84",
            "dur": "4.259",
            "text": "well it's entertaining and entertaining"
        },
        {
            "start": "128.899",
            "dur": "4.09",
            "text": "conflicts must have clear good and evil"
        },
        {
            "start": "131.099",
            "dur": "2.401",
            "text": "combatants because the media are corrupt"
        },
        {
            "start": "132.989",
            "dur": "2.491",
            "text": "in trouble"
        },
        {
            "start": "133.5",
            "dur": "3",
            "text": "mature both sides must willingly blind"
        },
        {
            "start": "135.48",
            "dur": "2.94",
            "text": "themselves to the faults of their"
        },
        {
            "start": "136.5",
            "dur": "3.42",
            "text": "favorite characters so the right says"
        },
        {
            "start": "138.42",
            "dur": "3.63",
            "text": "the Trump of the virginal political"
        },
        {
            "start": "139.92",
            "dur": "4.98",
            "text": "victim a neophyte undeserving of his"
        },
        {
            "start": "142.05",
            "dur": "4.53",
            "text": "critics vitriol even better he's held up"
        },
        {
            "start": "144.9",
            "dur": "3.06",
            "text": "as an unparalleled political genius the"
        },
        {
            "start": "146.58",
            "dur": "2.76",
            "text": "voice of the people the populist"
        },
        {
            "start": "147.96",
            "dur": "2.999",
            "text": "revolutionary and the guise of the"
        },
        {
            "start": "149.34",
            "dur": "3.33",
            "text": "prince of the city a sort of Bruce Wayne"
        },
        {
            "start": "150.959",
            "dur": "3.451",
            "text": "who down at the Cape of Justice by night"
        },
        {
            "start": "152.67",
            "dur": "3.27",
            "text": "and tweets raged the media by day while"
        },
        {
            "start": "154.41",
            "dur": "3.18",
            "text": "the music from The Dark Knight thunders"
        },
        {
            "start": "155.94",
            "dur": "2.94",
            "text": "dramatically in the background the hand"
        },
        {
            "start": "157.59",
            "dur": "3.45",
            "text": "will affect from stopping the Joker"
        },
        {
            "start": "158.88",
            "dur": "4.29",
            "text": "Hillary never fades in the eyes of Trump"
        },
        {
            "start": "161.04",
            "dur": "4.08",
            "text": "supporters meanwhile the press overlooks"
        },
        {
            "start": "163.17",
            "dur": "4.08",
            "text": "its own participation in the corrupted"
        },
        {
            "start": "165.12",
            "dur": "3.39",
            "text": "political entertainment complex in order"
        },
        {
            "start": "167.25",
            "dur": "3.09",
            "text": "to paint itself as thoroughly"
        },
        {
            "start": "168.51",
            "dur": "3.63",
            "text": "painstaking an objective in its work"
        },
        {
            "start": "170.34",
            "dur": "3.33",
            "text": "journalists see themselves and left"
        },
        {
            "start": "172.14",
            "dur": "3.84",
            "text": "flatteringly sees the journalists as"
        },
        {
            "start": "173.67",
            "dur": "4.02",
            "text": "warriors for truth exposing the light in"
        },
        {
            "start": "175.98",
            "dur": "3.3",
            "text": "every dark nook and cranny of the Trump"
        },
        {
            "start": "177.69",
            "dur": "3.51",
            "text": "administration they imagine themselves"
        },
        {
            "start": "179.28",
            "dur": "4.2",
            "text": "in battered hats and trench coats"
        },
        {
            "start": "181.2",
            "dur": "4.08",
            "text": "walking around in the rain looking for"
        },
        {
            "start": "183.48",
            "dur": "3.69",
            "text": "all of the evidence of the dark deeds"
        },
        {
            "start": "185.28",
            "dur": "3.75",
            "text": "uncovering the seedy side of Trump aney"
        },
        {
            "start": "187.17",
            "dur": "3.33",
            "text": "Hall the halo effect from opposing Trump"
        },
        {
            "start": "189.03",
            "dur": "3.99",
            "text": "never dies further the Fourth Estate"
        },
        {
            "start": "190.5",
            "dur": "4.68",
            "text": "this Manicheans dichotomy means that"
        },
        {
            "start": "193.02",
            "dur": "4.29",
            "text": "there is no way for any reasonable or"
        },
        {
            "start": "195.18",
            "dur": "3.96",
            "text": "tempered debate to emerge over proper"
        },
        {
            "start": "197.31",
            "dur": "3.54",
            "text": "behavior or coverage instead there's"
        },
        {
            "start": "199.14",
            "dur": "3.36",
            "text": "Glee for Trump's base in watching Trump"
        },
        {
            "start": "200.85",
            "dur": "3.72",
            "text": "bring justice to the streets of media"
        },
        {
            "start": "202.5",
            "dur": "3.63",
            "text": "Gotham winning VAT orangs masseur back"
        },
        {
            "start": "204.57",
            "dur": "3.66",
            "text": "nastiness at Mika Brzezinski's bloody"
        },
        {
            "start": "206.13",
            "dur": "3.81",
            "text": "face and for the media there is similar"
        },
        {
            "start": "208.23",
            "dur": "3.509",
            "text": "Glee in proclaiming Trump and incipient"
        },
        {
            "start": "209.94",
            "dur": "3.21",
            "text": "Hitler a Willie Stark who must be"
        },
        {
            "start": "211.739",
            "dur": "3.391",
            "text": "stopped before it can transform into"
        },
        {
            "start": "213.15",
            "dur": "3.33",
            "text": "real life Huey Long all of this makes"
        },
        {
            "start": "215.13",
            "dur": "3.63",
            "text": "the political scene a lot more fun and"
        },
        {
            "start": "216.48",
            "dur": "3.9",
            "text": "entertaining but it's not very useful"
        },
        {
            "start": "218.76",
            "dur": "3.72",
            "text": "well the drama of Trump versus the media"
        },
        {
            "start": "220.38",
            "dur": "3.6",
            "text": "is amusing it's not quite WWE quality"
        },
        {
            "start": "222.48",
            "dur": "3.36",
            "text": "because most people actually think that"
        },
        {
            "start": "223.98",
            "dur": "3.569",
            "text": "it's real we can find the WWE"
        },
        {
            "start": "225.84",
            "dur": "3.179",
            "text": "entertaining and amusing because we know"
        },
        {
            "start": "227.549",
            "dur": "3.091",
            "text": "it's scripted but if we actually thought"
        },
        {
            "start": "229.019",
            "dur": "3.511",
            "text": "it was real and then all of a sudden we"
        },
        {
            "start": "230.64",
            "dur": "3.48",
            "text": "were rudely disabused of that notion it"
        },
        {
            "start": "232.53",
            "dur": "3",
            "text": "would probably ruin the fun the same is"
        },
        {
            "start": "234.12",
            "dur": "3.33",
            "text": "true of our politics right now the"
        },
        {
            "start": "235.53",
            "dur": "3.48",
            "text": "realization that Trump versus the media"
        },
        {
            "start": "237.45",
            "dur": "2.789",
            "text": "is just overblown stupidity half"
        },
        {
            "start": "239.01",
            "dur": "3.06",
            "text": "scripted on both sides makes the"
        },
        {
            "start": "240.239",
            "dur": "3.571",
            "text": "conflict less compelling the comedy"
        },
        {
            "start": "242.07",
            "dur": "3.18",
            "text": "actually becomes kind of tragic after"
        },
        {
            "start": "243.81",
            "dur": "3.48",
            "text": "all it's a lot easier to laugh at the"
        },
        {
            "start": "245.25",
            "dur": "3.48",
            "text": "antics of the undertake Undertaker than"
        },
        {
            "start": "247.29",
            "dur": "2.85",
            "text": "to laugh as the office of George"
        },
        {
            "start": "248.73",
            "dur": "3.42",
            "text": "Washington and the industry of ernie"
        },
        {
            "start": "250.14",
            "dur": "5.36",
            "text": "pyle both become punchlines i'm ben"
        },
        {
            "start": "252.15",
            "dur": "3.35",
            "text": "shapiro this is the Ben Shapiro show"
        },
        {
            "start": "258.67",
            "dur": "4.03",
            "text": "okay so the CNN has completely let"
        },
        {
            "start": "260.93",
            "dur": "4.26",
            "text": "itself on fire so yesterday was July 4th"
        },
        {
            "start": "262.7",
            "dur": "3.96",
            "text": "and in honor of Independence Day she and"
        },
        {
            "start": "265.19",
            "dur": "3.51",
            "text": "then held the fireworks celebration in"
        },
        {
            "start": "266.66",
            "dur": "3.84",
            "text": "its own pants it lit all of the TNT that"
        },
        {
            "start": "268.7",
            "dur": "3.93",
            "text": "I could find and then proceeded to blow"
        },
        {
            "start": "270.5",
            "dur": "3.69",
            "text": "it up absolutely destroying itself"
        },
        {
            "start": "272.63",
            "dur": "3.15",
            "text": "wholesale we will talk about all of it"
        },
        {
            "start": "274.19",
            "dur": "2.82",
            "text": "because it is really amusing I just said"
        },
        {
            "start": "275.78",
            "dur": "3.15",
            "text": "we shouldn't talk so much about the WWE"
        },
        {
            "start": "277.01",
            "dur": "3.12",
            "text": "stuff but I'm going to because it's"
        },
        {
            "start": "278.93",
            "dur": "3.21",
            "text": "hilarious oh we'll talk about all of"
        },
        {
            "start": "280.13",
            "dur": "3.93",
            "text": "that stuff in a second but first I want"
        },
        {
            "start": "282.14",
            "dur": "4.17",
            "text": "to say thank you to our sponsors over at"
        },
        {
            "start": "284.06",
            "dur": "3.63",
            "text": "blinds comm so I'm sure you don't think"
        },
        {
            "start": "286.31",
            "dur": "2.97",
            "text": "too much about your blinds but let's"
        },
        {
            "start": "287.69",
            "dur": "3",
            "text": "face it they're really ugly and you need"
        },
        {
            "start": "289.28",
            "dur": "2.82",
            "text": "to replace them because they've been"
        },
        {
            "start": "290.69",
            "dur": "2.73",
            "text": "there for like 20 years and they're left"
        },
        {
            "start": "292.1",
            "dur": "2.49",
            "text": "over from the previous tenants or the"
        },
        {
            "start": "293.42",
            "dur": "2.97",
            "text": "previous owner you never bothered"
        },
        {
            "start": "294.59",
            "dur": "3.33",
            "text": "because who cares about blind you should"
        },
        {
            "start": "296.39",
            "dur": "3.84",
            "text": "care about blinds because they make your"
        },
        {
            "start": "297.92",
            "dur": "3.99",
            "text": "home look so much better when they are"
        },
        {
            "start": "300.23",
            "dur": "3.27",
            "text": "bad you need to replace them as what"
        },
        {
            "start": "301.91",
            "dur": "3.21",
            "text": "blind scum does for you they make it"
        },
        {
            "start": "303.5",
            "dur": "3.15",
            "text": "really easy if you're not sure what you"
        },
        {
            "start": "305.12",
            "dur": "3.3",
            "text": "want or even where to start you go to"
        },
        {
            "start": "306.65",
            "dur": "3.39",
            "text": "blind comm you get a free online design"
        },
        {
            "start": "308.42",
            "dur": "3.06",
            "text": "consultation that you send them pictures"
        },
        {
            "start": "310.04",
            "dur": "2.76",
            "text": "of your house they don't send back"
        },
        {
            "start": "311.48",
            "dur": "2.91",
            "text": "custom recommendations from a"
        },
        {
            "start": "312.8",
            "dur": "3.15",
            "text": "professional for what will work with"
        },
        {
            "start": "314.39",
            "dur": "3.75",
            "text": "your color scheme your furniture"
        },
        {
            "start": "315.95",
            "dur": "3.54",
            "text": "specific rooms but we even send you free"
        },
        {
            "start": "318.14",
            "dur": "3.24",
            "text": "samples to make sure that what you see"
        },
        {
            "start": "319.49",
            "dur": "3.93",
            "text": "online actually looks as good in person"
        },
        {
            "start": "321.38",
            "dur": "3.18",
            "text": "as it does online and if you miss"
        },
        {
            "start": "323.42",
            "dur": "3.27",
            "text": "measure you measure it yourself even"
        },
        {
            "start": "324.56",
            "dur": "4.29",
            "text": "this measure it blinds will blinds comm"
        },
        {
            "start": "326.69",
            "dur": "3.81",
            "text": "will remake the blinds for free so you"
        },
        {
            "start": "328.85",
            "dur": "3.18",
            "text": "can screw it up and it's your fault they"
        },
        {
            "start": "330.5",
            "dur": "2.91",
            "text": "will make sure that it gets done right"
        },
        {
            "start": "332.03",
            "dur": "3.03",
            "text": "for a limited time go over to blinds"
        },
        {
            "start": "333.41",
            "dur": "4.47",
            "text": "comm and use the promo code band you get"
        },
        {
            "start": "335.06",
            "dur": "4.74",
            "text": "20% off everything all of the things 20%"
        },
        {
            "start": "337.88",
            "dur": "3.9",
            "text": "off when you go to blinds comm using"
        },
        {
            "start": "339.8",
            "dur": "3.54",
            "text": "promo code then again that's faux wood"
        },
        {
            "start": "341.78",
            "dur": "3.51",
            "text": "blinds cellular shades roller shades and"
        },
        {
            "start": "343.34",
            "dur": "4.2",
            "text": "more 20% off everything when you use"
        },
        {
            "start": "345.29",
            "dur": "3.9",
            "text": "blinds calm promo code Ben again that's"
        },
        {
            "start": "347.54",
            "dur": "3.36",
            "text": "blind SATCOM promo code Ben rules and"
        },
        {
            "start": "349.19",
            "dur": "2.97",
            "text": "restrictions do apply but make sure you"
        },
        {
            "start": "350.9",
            "dur": "2.67",
            "text": "use that promo code Ben so they know"
        },
        {
            "start": "352.16",
            "dur": "4.83",
            "text": "that we sent you and you helped support"
        },
        {
            "start": "353.57",
            "dur": "5.94",
            "text": "the program okay so CNN just it's"
        },
        {
            "start": "356.99",
            "dur": "6.06",
            "text": "astonishing how basically I tweeted last"
        },
        {
            "start": "359.51",
            "dur": "5.22",
            "text": "week that Trump destroyed CNN not by"
        },
        {
            "start": "363.05",
            "dur": "2.79",
            "text": "actually attacking them by trolling them"
        },
        {
            "start": "364.73",
            "dur": "2.88",
            "text": "so hard that they destroyed themselves"
        },
        {
            "start": "365.84",
            "dur": "2.97",
            "text": "he really gave them enough rope that"
        },
        {
            "start": "367.61",
            "dur": "3.24",
            "text": "they decided not just to hang themselves"
        },
        {
            "start": "368.81",
            "dur": "3.39",
            "text": "but to hang themselves by the neck until"
        },
        {
            "start": "370.85",
            "dur": "3.24",
            "text": "they were nearly dead then pull"
        },
        {
            "start": "372.2",
            "dur": "3.9",
            "text": "themselves up back onto the platform and"
        },
        {
            "start": "374.09",
            "dur": "3.75",
            "text": "jump repeatedly this is basically what"
        },
        {
            "start": "376.1",
            "dur": "2.37",
            "text": "CNN is doing now so here's how this"
        },
        {
            "start": "377.84",
            "dur": "2.51",
            "text": "works out"
        },
        {
            "start": "378.47",
            "dur": "4.77",
            "text": "over the course of the weekend so on"
        },
        {
            "start": "380.35",
            "dur": "4.99",
            "text": "Sunday president Trump tweets something"
        },
        {
            "start": "383.24",
            "dur": "3.42",
            "text": "that I assume my three and a half year"
        },
        {
            "start": "385.34",
            "dur": "3.86",
            "text": "old daughter has the good sense not to"
        },
        {
            "start": "386.66",
            "dur": "6.71",
            "text": "tweet a WWE wrestling graphic"
        },
        {
            "start": "389.2",
            "dur": "6.12",
            "text": "of himself tackling a person with a CNN"
        },
        {
            "start": "393.37",
            "dur": "3",
            "text": "logo for a head and then jumping on top"
        },
        {
            "start": "395.32",
            "dur": "2.88",
            "text": "of them and pummeling them right the"
        },
        {
            "start": "396.37",
            "dur": "3.24",
            "text": "President of the United States let me"
        },
        {
            "start": "398.2",
            "dur": "3.54",
            "text": "forget George Washington and Abraham"
        },
        {
            "start": "399.61",
            "dur": "3.51",
            "text": "Lincoln once sat well George Washington"
        },
        {
            "start": "401.74",
            "dur": "3.99",
            "text": "did but Abraham Lincoln once sat in the"
        },
        {
            "start": "403.12",
            "dur": "4.83",
            "text": "office where Joe where Donald Trump is"
        },
        {
            "start": "405.73",
            "dur": "4.32",
            "text": "tweeting in the middle of the night from"
        },
        {
            "start": "407.95",
            "dur": "3.39",
            "text": "the toilet presumably about racially so"
        },
        {
            "start": "410.05",
            "dur": "14.01",
            "text": "so he tweets this and here's what it"
        },
        {
            "start": "411.34",
            "dur": "15.72",
            "text": "looks like everything is so stupid okay"
        },
        {
            "start": "424.06",
            "dur": "4.77",
            "text": "so he tweets that and then he and then"
        },
        {
            "start": "427.06",
            "dur": "3.03",
            "text": "he enjoy for its independence day he"
        },
        {
            "start": "428.83",
            "dur": "2.46",
            "text": "said to double down on that he starts"
        },
        {
            "start": "430.09",
            "dur": "3.15",
            "text": "mocking the fake media which is his"
        },
        {
            "start": "431.29",
            "dur": "3.69",
            "text": "favorite thing to do right he's he North"
        },
        {
            "start": "433.24",
            "dur": "2.79",
            "text": "Korea may be firing the intercontinental"
        },
        {
            "start": "434.98",
            "dur": "3.18",
            "text": "ballistic missile capable of hitting"
        },
        {
            "start": "436.03",
            "dur": "3.57",
            "text": "Alaska but he's got to hit the fake"
        },
        {
            "start": "438.16",
            "dur": "2.97",
            "text": "media I mean come on so it's the"
        },
        {
            "start": "439.6",
            "dur": "3.15",
            "text": "Independence Day and in the middle of it"
        },
        {
            "start": "441.13",
            "dur": "4.65",
            "text": "see she jumped out that he starts"
        },
        {
            "start": "442.75",
            "dur": "7.59",
            "text": "ripping on the fake media all right the"
        },
        {
            "start": "445.78",
            "dur": "9.96",
            "text": "fake media is trying to silence us but"
        },
        {
            "start": "450.34",
            "dur": "10.14",
            "text": "we will not let them because the people"
        },
        {
            "start": "455.74",
            "dur": "7.7",
            "text": "know the truth the fake media tried to"
        },
        {
            "start": "460.48",
            "dur": "7.2",
            "text": "stop us from going to the White House"
        },
        {
            "start": "463.44",
            "dur": "5.62",
            "text": "but I'm president and they're not okay"
        },
        {
            "start": "467.68",
            "dur": "2.55",
            "text": "so that's their I mean the media hated"
        },
        {
            "start": "469.06",
            "dur": "2.19",
            "text": "him they tried to stop him from going to"
        },
        {
            "start": "470.23",
            "dur": "2.4",
            "text": "the White House and now they're trying"
        },
        {
            "start": "471.25",
            "dur": "3",
            "text": "to take him down all that is fair"
        },
        {
            "start": "472.63",
            "dur": "3.66",
            "text": "they're not exactly silencing him he's"
        },
        {
            "start": "474.25",
            "dur": "3.87",
            "text": "pretty loud it turns out and he uses his"
        },
        {
            "start": "476.29",
            "dur": "3.78",
            "text": "Twitter a lot so that really doesn't"
        },
        {
            "start": "478.12",
            "dur": "3.54",
            "text": "change anything but yes the media are"
        },
        {
            "start": "480.07",
            "dur": "5.58",
            "text": "bad yes the media are obviously trying"
        },
        {
            "start": "481.66",
            "dur": "5.4",
            "text": "to cover him in unfair fashion so he"
        },
        {
            "start": "485.65",
            "dur": "3.84",
            "text": "tweets this stupid thing about wrestling"
        },
        {
            "start": "487.06",
            "dur": "4.05",
            "text": "the media has an obvious response they"
        },
        {
            "start": "489.49",
            "dur": "3.69",
            "text": "could say mr. president that was a"
        },
        {
            "start": "491.11",
            "dur": "4.38",
            "text": "stupid thing to tweet maybe you don't"
        },
        {
            "start": "493.18",
            "dur": "4.17",
            "text": "have a lot of self-control that would be"
        },
        {
            "start": "495.49",
            "dur": "4.11",
            "text": "true it would also be obvious and it"
        },
        {
            "start": "497.35",
            "dur": "3.99",
            "text": "would be relatively objective instead"
        },
        {
            "start": "499.6",
            "dur": "3.42",
            "text": "they proceeded to spend the next three"
        },
        {
            "start": "501.34",
            "dur": "3.6",
            "text": "days talking about how this means that"
        },
        {
            "start": "503.02",
            "dur": "4.14",
            "text": "Donald Trump wants to literally go and"
        },
        {
            "start": "504.94",
            "dur": "4.05",
            "text": "beat brian Stelter spacing right it"
        },
        {
            "start": "507.16",
            "dur": "3.27",
            "text": "really he's a sick Nazi who wants to"
        },
        {
            "start": "508.99",
            "dur": "3.72",
            "text": "murder people and that's why he's"
        },
        {
            "start": "510.43",
            "dur": "4.98",
            "text": "tweeting outwrestling tweets from the"
        },
        {
            "start": "512.71",
            "dur": "3.93",
            "text": "WWE like I'm first of all it doesn't"
        },
        {
            "start": "515.41",
            "dur": "3.41",
            "text": "make any sense to me they use the CNN"
        },
        {
            "start": "516.64",
            "dur": "4.86",
            "text": "logo over at Miz Vince McMahon's face is"
        },
        {
            "start": "518.82",
            "dur": "4.27",
            "text": "CNN's logo a person like how can you"
        },
        {
            "start": "521.5",
            "dur": "3.18",
            "text": "even hit CNN's logo it's a"
        },
        {
            "start": "523.09",
            "dur": "4.59",
            "text": "it's not a say it's not a person like"
        },
        {
            "start": "524.68",
            "dur": "5.099",
            "text": "how unless brian Stelter changed his"
        },
        {
            "start": "527.68",
            "dur": "3.39",
            "text": "face and had surgery I can old Twilight"
        },
        {
            "start": "529.779",
            "dur": "2.731",
            "text": "Zone episodes and now his face looks"
        },
        {
            "start": "531.07",
            "dur": "2.91",
            "text": "like the CNN logo I don't see how anyone"
        },
        {
            "start": "532.51",
            "dur": "3.51",
            "text": "would identify one with the other but in"
        },
        {
            "start": "533.98",
            "dur": "3.72",
            "text": "any case the left went hysterical so"
        },
        {
            "start": "536.02",
            "dur": "2.94",
            "text": "Howard Dean says it's just right-wingers"
        },
        {
            "start": "537.7",
            "dur": "2.85",
            "text": "and they want to shoot places up it's"
        },
        {
            "start": "538.96",
            "dur": "3.24",
            "text": "all because of Trump it's Trump and he's"
        },
        {
            "start": "540.55",
            "dur": "4.59",
            "text": "a Nazi so it's not enough for them just"
        },
        {
            "start": "542.2",
            "dur": "4.53",
            "text": "to say that Trump is is ridiculous in"
        },
        {
            "start": "545.14",
            "dur": "3.78",
            "text": "how he uses Twitter which is obviously"
        },
        {
            "start": "546.73",
            "dur": "3.21",
            "text": "for no no he's evil and he's a Nazi and"
        },
        {
            "start": "548.92",
            "dur": "2.25",
            "text": "then you'll see they went even further"
        },
        {
            "start": "549.94",
            "dur": "1.89",
            "text": "because they're totally insane they've"
        },
        {
            "start": "551.17",
            "dur": "2.28",
            "text": "lost their minds"
        },
        {
            "start": "551.83",
            "dur": "2.94",
            "text": "Trump has trolled them so hard that they"
        },
        {
            "start": "553.45",
            "dur": "3.06",
            "text": "have actually become that which they"
        },
        {
            "start": "554.77",
            "dur": "5.009",
            "text": "fear so here is Howard Dean first saying"
        },
        {
            "start": "556.51",
            "dur": "4.95",
            "text": "that Trump is evil and violent a lot of"
        },
        {
            "start": "559.779",
            "dur": "4.111",
            "text": "the Trump voters are not the far-right"
        },
        {
            "start": "561.46",
            "dur": "3.54",
            "text": "nutcases with guns who want to you know"
        },
        {
            "start": "563.89",
            "dur": "3.33",
            "text": "shoot up the place"
        },
        {
            "start": "565",
            "dur": "5.61",
            "text": "most of the Trump voters are be anyone"
        },
        {
            "start": "567.22",
            "dur": "5.55",
            "text": "was defining them that way know what"
        },
        {
            "start": "570.61",
            "dur": "4.14",
            "text": "there certainly are some of them and the"
        },
        {
            "start": "572.77",
            "dur": "4.98",
            "text": "NRA put an appalling ad out there which"
        },
        {
            "start": "574.75",
            "dur": "4.529",
            "text": "really didn't basically made this a mini"
        },
        {
            "start": "577.75",
            "dur": "3.45",
            "text": "okay so what the Howard Dean who's a"
        },
        {
            "start": "579.279",
            "dur": "3.241",
            "text": "complete is talking about how the"
        },
        {
            "start": "581.2",
            "dur": "3.81",
            "text": "right is full of violent people"
        },
        {
            "start": "582.52",
            "dur": "4.59",
            "text": "let us unless we forget three weeks ago"
        },
        {
            "start": "585.01",
            "dur": "3.6",
            "text": "a Trump hating Bernie Sanders supporter"
        },
        {
            "start": "587.11",
            "dur": "3.36",
            "text": "tried to assassinate several dozen"
        },
        {
            "start": "588.61",
            "dur": "2.79",
            "text": "Republican Congress people but were the"
        },
        {
            "start": "590.47",
            "dur": "2.43",
            "text": "violent ones right"
        },
        {
            "start": "591.4",
            "dur": "2.91",
            "text": "it's the Trump supporters who are the"
        },
        {
            "start": "592.9",
            "dur": "3.6",
            "text": "violent ones those of us on the right"
        },
        {
            "start": "594.31",
            "dur": "3.99",
            "text": "who are the violent ones okay so Trump"
        },
        {
            "start": "596.5",
            "dur": "3.57",
            "text": "tweets out this WW thing and medias"
        },
        {
            "start": "598.3",
            "dur": "3.9",
            "text": "first reaction is Trump is violent and"
        },
        {
            "start": "600.07",
            "dur": "3.269",
            "text": "then they get their second reaction so"
        },
        {
            "start": "602.2",
            "dur": "2.85",
            "text": "it's not enough for them to be clown"
        },
        {
            "start": "603.339",
            "dur": "3.091",
            "text": "themselves the first way they have to"
        },
        {
            "start": "605.05",
            "dur": "3",
            "text": "proclaim themselves every way they have"
        },
        {
            "start": "606.43",
            "dur": "4.05",
            "text": "to find new ways to bolon themselves"
        },
        {
            "start": "608.05",
            "dur": "6.48",
            "text": "every single day so what do they do"
        },
        {
            "start": "610.48",
            "dur": "5.88",
            "text": "CNN goes CNN goes ahead and runs a story"
        },
        {
            "start": "614.53",
            "dur": "3.36",
            "text": "trying to find the source of the main"
        },
        {
            "start": "616.36",
            "dur": "3.21",
            "text": "right because Trump didn't create this"
        },
        {
            "start": "617.89",
            "dur": "4.32",
            "text": "little video of himself tackling the CNN"
        },
        {
            "start": "619.57",
            "dur": "4.29",
            "text": "logo somebody took the WWE video and"
        },
        {
            "start": "622.21",
            "dur": "3.48",
            "text": "pasted the CN and logo in there so where"
        },
        {
            "start": "623.86",
            "dur": "4.02",
            "text": "did he get it so he got it supposedly"
        },
        {
            "start": "625.69",
            "dur": "3.33",
            "text": "according to CNN from some guy at reddit"
        },
        {
            "start": "627.88",
            "dur": "3.84",
            "text": "for those who don't know reddit sort of"
        },
        {
            "start": "629.02",
            "dur": "4.29",
            "text": "an underground political thread it's"
        },
        {
            "start": "631.72",
            "dur": "3.84",
            "text": "very big website a lot people visit it"
        },
        {
            "start": "633.31",
            "dur": "4.02",
            "text": "are the Donald is where all of these"
        },
        {
            "start": "635.56",
            "dur": "2.97",
            "text": "memes pop up and I sort of have a"
        },
        {
            "start": "637.33",
            "dur": "2.4",
            "text": "love-hate relationship with other than"
        },
        {
            "start": "638.53",
            "dur": "1.65",
            "text": "Arnold sometimes they like me sometimes"
        },
        {
            "start": "639.73",
            "dur": "2.31",
            "text": "they don't"
        },
        {
            "start": "640.18",
            "dur": "3.87",
            "text": "it's always an inverse relationship with"
        },
        {
            "start": "642.04",
            "dur": "3.66",
            "text": "how nice I'm being to Trump that day so"
        },
        {
            "start": "644.05",
            "dur": "4.17",
            "text": "I'm sure they'll love this episode in"
        },
        {
            "start": "645.7",
            "dur": "4.8",
            "text": "any case are the Donald posts this meme"
        },
        {
            "start": "648.22",
            "dur": "4.29",
            "text": "there's a guy whose name is I can't"
        },
        {
            "start": "650.5",
            "dur": "5.07",
            "text": "actually say it out loud because it's"
        },
        {
            "start": "652.51",
            "dur": "4.139",
            "text": "cursing it's Han bleep whole solo okay"
        },
        {
            "start": "655.57",
            "dur": "2.22",
            "text": "and this is now national"
        },
        {
            "start": "656.649",
            "dur": "4.141",
            "text": "media coverage we have to discuss these"
        },
        {
            "start": "657.79",
            "dur": "5.609",
            "text": "things because this is everything is"
        },
        {
            "start": "660.79",
            "dur": "4.44",
            "text": "stupid so he puts out this meme right"
        },
        {
            "start": "663.399",
            "dur": "4.86",
            "text": "hon bleep hole solo puts out this meme"
        },
        {
            "start": "665.23",
            "dur": "4.44",
            "text": "and CNN traces it back to him and then"
        },
        {
            "start": "668.259",
            "dur": "2.61",
            "text": "CNN goes and looks at all the other"
        },
        {
            "start": "669.67",
            "dur": "2.279",
            "text": "memes that he's put out and turns out"
        },
        {
            "start": "670.869",
            "dur": "2.431",
            "text": "he's put out a bunch of racist"
        },
        {
            "start": "671.949",
            "dur": "2.64",
            "text": "anti-semitic names because there are a"
        },
        {
            "start": "673.3",
            "dur": "2.459",
            "text": "lot of people on reddit who do this I"
        },
        {
            "start": "674.589",
            "dur": "3.3",
            "text": "know because I was the personal"
        },
        {
            "start": "675.759",
            "dur": "4.2",
            "text": "recipient a 40% of all anti-semitic"
        },
        {
            "start": "677.889",
            "dur": "4.14",
            "text": "memes that were tweeted on the Internet"
        },
        {
            "start": "679.959",
            "dur": "3.511",
            "text": "at journalists last year I personally"
        },
        {
            "start": "682.029",
            "dur": "3.78",
            "text": "was the recipient of so I'm well aware"
        },
        {
            "start": "683.47",
            "dur": "3.599",
            "text": "of this entire crowd I mean well aware"
        },
        {
            "start": "685.809",
            "dur": "3.75",
            "text": "of the bleep posters as they call"
        },
        {
            "start": "687.069",
            "dur": "4.291",
            "text": "themselves in any case they decide to"
        },
        {
            "start": "689.559",
            "dur": "3.421",
            "text": "dig up all of this ancillary material"
        },
        {
            "start": "691.36",
            "dur": "3.089",
            "text": "and then pretend that Trump is somehow"
        },
        {
            "start": "692.98",
            "dur": "3.06",
            "text": "linked to that so first of all this is"
        },
        {
            "start": "694.449",
            "dur": "2.76",
            "text": "bad journalism it's bad journalism"
        },
        {
            "start": "696.04",
            "dur": "3.029",
            "text": "because it would be one thing if Trump"
        },
        {
            "start": "697.209",
            "dur": "3.63",
            "text": "tweeted an anti-semitic meme and then"
        },
        {
            "start": "699.069",
            "dur": "3.24",
            "text": "they said okay here is the world of ants"
        },
        {
            "start": "700.839",
            "dur": "3.54",
            "text": "Medic memes from which he is drawing"
        },
        {
            "start": "702.309",
            "dur": "4.111",
            "text": "that would be able to good story right"
        },
        {
            "start": "704.379",
            "dur": "3.721",
            "text": "or if they'd said he keeps going over to"
        },
        {
            "start": "706.42",
            "dur": "3.329",
            "text": "Reddit and 4chan he has a long-standing"
        },
        {
            "start": "708.1",
            "dur": "3.239",
            "text": "relationship with Reddit and 4chan where"
        },
        {
            "start": "709.749",
            "dur": "3.27",
            "text": "he takes their memes why is he so warm"
        },
        {
            "start": "711.339",
            "dur": "3.81",
            "text": "toward these people that's a fair story"
        },
        {
            "start": "713.019",
            "dur": "3.57",
            "text": "what is not a fair story is he picks up"
        },
        {
            "start": "715.149",
            "dur": "3.271",
            "text": "one piece of material from the art"
        },
        {
            "start": "716.589",
            "dur": "3.331",
            "text": "Donald thread and now we're going to"
        },
        {
            "start": "718.42",
            "dur": "3.269",
            "text": "find the person who created that who"
        },
        {
            "start": "719.92",
            "dur": "4.529",
            "text": "Trump has never met probably never seen"
        },
        {
            "start": "721.689",
            "dur": "3.84",
            "text": "and never in none of this came like some"
        },
        {
            "start": "724.449",
            "dur": "2.37",
            "text": "probably had no relationship with this"
        },
        {
            "start": "725.529",
            "dur": "3.15",
            "text": "person ever he doesn't know who they are"
        },
        {
            "start": "726.819",
            "dur": "3.99",
            "text": "from Adam and then we're going to find"
        },
        {
            "start": "728.679",
            "dur": "3.6",
            "text": "everything that guy ever did and then we"
        },
        {
            "start": "730.809",
            "dur": "3.421",
            "text": "are going to wink all the bad things"
        },
        {
            "start": "732.279",
            "dur": "3.24",
            "text": "that I did with Trump right you can see"
        },
        {
            "start": "734.23",
            "dur": "2.909",
            "text": "how far they're stretching so already"
        },
        {
            "start": "735.519",
            "dur": "3.12",
            "text": "this is a stupid story already this is"
        },
        {
            "start": "737.139",
            "dur": "2.88",
            "text": "an idiotic story Trump didn't tweet"
        },
        {
            "start": "738.639",
            "dur": "2.88",
            "text": "anything racist or anti-semitic he"
        },
        {
            "start": "740.019",
            "dur": "2.67",
            "text": "tweeted something dumb and now they're"
        },
        {
            "start": "741.519",
            "dur": "2.91",
            "text": "trying to link him with racism and"
        },
        {
            "start": "742.689",
            "dur": "4.59",
            "text": "anti-semitism because the original"
        },
        {
            "start": "744.429",
            "dur": "5.88",
            "text": "creator of this wrestling Jeff gif was"
        },
        {
            "start": "747.279",
            "dur": "5.191",
            "text": "was some schmuck who tweets out"
        },
        {
            "start": "750.309",
            "dur": "4.38",
            "text": "anti-semitic racist stuff okay so that's"
        },
        {
            "start": "752.47",
            "dur": "4.02",
            "text": "dumb in and of itself but then they go a"
        },
        {
            "start": "754.689",
            "dur": "3.12",
            "text": "level dumber okay I told you things are"
        },
        {
            "start": "756.49",
            "dur": "1.649",
            "text": "just going to get stupider from here on"
        },
        {
            "start": "757.809",
            "dur": "1.97",
            "text": "it"
        },
        {
            "start": "758.139",
            "dur": "3.66",
            "text": "right eventually as I said last week"
        },
        {
            "start": "759.779",
            "dur": "4",
            "text": "America will disappear because we all go"
        },
        {
            "start": "761.799",
            "dur": "3.691",
            "text": "brain dead from loss of IQ points due to"
        },
        {
            "start": "763.779",
            "dur": "3.9",
            "text": "following politics too closely because"
        },
        {
            "start": "765.49",
            "dur": "4.98",
            "text": "this is all so stupid so it goes a level"
        },
        {
            "start": "767.679",
            "dur": "4.861",
            "text": "deeper in the stupidity so now CNN"
        },
        {
            "start": "770.47",
            "dur": "4.289",
            "text": "doesn't just crack down on a whole solos"
        },
        {
            "start": "772.54",
            "dur": "2.759",
            "text": "name right they tread dancers track down"
        },
        {
            "start": "774.759",
            "dur": "2.37",
            "text": "who he is"
        },
        {
            "start": "775.299",
            "dur": "5.58",
            "text": "they don't just track down what else"
        },
        {
            "start": "777.129",
            "dur": "5.281",
            "text": "he's tweeted now they go to him and they"
        },
        {
            "start": "780.879",
            "dur": "2.55",
            "text": "reach out to him and he immediately sees"
        },
        {
            "start": "782.41",
            "dur": "2.549",
            "text": "what's happening he sees they're not"
        },
        {
            "start": "783.429",
            "dur": "3.541",
            "text": "going to target him and so what he"
        },
        {
            "start": "784.959",
            "dur": "3.641",
            "text": "decides to do is apologize so he puts a"
        },
        {
            "start": "786.97",
            "dur": "3.22",
            "text": "big apology he takes down"
        },
        {
            "start": "788.6",
            "dur": "3.45",
            "text": "all the terrible tweets it takes then"
        },
        {
            "start": "790.19",
            "dur": "3.389",
            "text": "all of the terrible memes and then CNN"
        },
        {
            "start": "792.05",
            "dur": "3.029",
            "text": "prints the story and here is what they"
        },
        {
            "start": "793.579",
            "dur": "3.99",
            "text": "print ok this is from the CNN story"
        },
        {
            "start": "795.079",
            "dur": "5.07",
            "text": "direct quote quote CNN is not publishing"
        },
        {
            "start": "797.569",
            "dur": "4.14",
            "text": "Han a-hole solos name because he is a"
        },
        {
            "start": "800.149",
            "dur": "3.511",
            "text": "private citizen who has issued an"
        },
        {
            "start": "801.709",
            "dur": "3.841",
            "text": "extensive statement of apology showed"
        },
        {
            "start": "803.66",
            "dur": "3.75",
            "text": "remorse by saying he has taken down all"
        },
        {
            "start": "805.55",
            "dur": "3.269",
            "text": "his offending posts and because he said"
        },
        {
            "start": "807.41",
            "dur": "3.03",
            "text": "he is not going to repeat this ugly"
        },
        {
            "start": "808.819",
            "dur": "3.481",
            "text": "behavior on social media again in"
        },
        {
            "start": "810.44",
            "dur": "3.48",
            "text": "addition he said his statement could"
        },
        {
            "start": "812.3",
            "dur": "1.979",
            "text": "serve as an example to others not to do"
        },
        {
            "start": "813.92",
            "dur": "3",
            "text": "the same"
        },
        {
            "start": "814.279",
            "dur": "6.36",
            "text": "CNN reserves the right to publish his"
        },
        {
            "start": "816.92",
            "dur": "5.279",
            "text": "identity should any of that change okay"
        },
        {
            "start": "820.639",
            "dur": "3.87",
            "text": "so for those of you who missed what just"
        },
        {
            "start": "822.199",
            "dur": "3.81",
            "text": "happened that's called blackmail right"
        },
        {
            "start": "824.509",
            "dur": "3.06",
            "text": "what CNN is doing now is they're now"
        },
        {
            "start": "826.009",
            "dur": "3",
            "text": "saying he took down all of the stuff"
        },
        {
            "start": "827.569",
            "dur": "3.361",
            "text": "that we didn't like he took the racist"
        },
        {
            "start": "829.009",
            "dur": "4.02",
            "text": "ancestry to come on CNN and stuff but"
        },
        {
            "start": "830.93",
            "dur": "3.93",
            "text": "should he renege should he become a"
        },
        {
            "start": "833.029",
            "dur": "3.781",
            "text": "recidivist a reddit recidivist he'd"
        },
        {
            "start": "834.86",
            "dur": "3.63",
            "text": "become a meme recidivist should he go"
        },
        {
            "start": "836.81",
            "dur": "4.56",
            "text": "out on the streets and threaten America"
        },
        {
            "start": "838.49",
            "dur": "5.7",
            "text": "America again with other WWE linked"
        },
        {
            "start": "841.37",
            "dur": "5.37",
            "text": "videos then we will reveal his name to"
        },
        {
            "start": "844.19",
            "dur": "4.649",
            "text": "the public at large right CNN reserves"
        },
        {
            "start": "846.74",
            "dur": "6.329",
            "text": "the right to publish his identity should"
        },
        {
            "start": "848.839",
            "dur": "5.791",
            "text": "any of that change what so now they've"
        },
        {
            "start": "853.069",
            "dur": "3.061",
            "text": "taken what was an obvious and clear win"
        },
        {
            "start": "854.63",
            "dur": "2.699",
            "text": "on Sunday right Trump making fun of them"
        },
        {
            "start": "856.13",
            "dur": "2.639",
            "text": "with some stupid meme and they could"
        },
        {
            "start": "857.329",
            "dur": "2.94",
            "text": "make fun of him back and it's an obvious"
        },
        {
            "start": "858.769",
            "dur": "3.57",
            "text": "one and they have destroyed themselves"
        },
        {
            "start": "860.269",
            "dur": "3.42",
            "text": "three separate ways first by claiming"
        },
        {
            "start": "862.339",
            "dur": "3.18",
            "text": "that Trump is violent and this is"
        },
        {
            "start": "863.689",
            "dur": "3.361",
            "text": "promoting violence second by trying to"
        },
        {
            "start": "865.519",
            "dur": "3.541",
            "text": "track down everything possible about"
        },
        {
            "start": "867.05",
            "dur": "3.57",
            "text": "this mean guy and third by then"
        },
        {
            "start": "869.06",
            "dur": "2.94",
            "text": "threatening the meme guy that if he"
        },
        {
            "start": "870.62",
            "dur": "4.05",
            "text": "doesn't back down from this they are"
        },
        {
            "start": "872",
            "dur": "4.11",
            "text": "going to out him right that is it so CNN"
        },
        {
            "start": "874.67",
            "dur": "3.57",
            "text": "has now blown all journalistic"
        },
        {
            "start": "876.11",
            "dur": "4.11",
            "text": "credibility out of some pathetic sick"
        },
        {
            "start": "878.24",
            "dur": "3.93",
            "text": "attempt to get Donald Trump and anyone"
        },
        {
            "start": "880.22",
            "dur": "4.53",
            "text": "who is remotely linked with Donald Trump"
        },
        {
            "start": "882.17",
            "dur": "4.44",
            "text": "that's how insane all of this is I mean"
        },
        {
            "start": "884.75",
            "dur": "2.939",
            "text": "it's totally crazy and this is what"
        },
        {
            "start": "886.61",
            "dur": "1.5",
            "text": "Santa's doing but wait it gets even"
        },
        {
            "start": "887.689",
            "dur": "2.041",
            "text": "better"
        },
        {
            "start": "888.11",
            "dur": "3.18",
            "text": "okay so just keep going the story gets"
        },
        {
            "start": "889.73",
            "dur": "3.599",
            "text": "even better but before I tell you the"
        },
        {
            "start": "891.29",
            "dur": "4.08",
            "text": "rest of the story I have to say thank"
        },
        {
            "start": "893.329",
            "dur": "4.351",
            "text": "you to our sponsors over a tracker so I"
        },
        {
            "start": "895.37",
            "dur": "4.29",
            "text": "am a person who is incredibly"
        },
        {
            "start": "897.68",
            "dur": "3.599",
            "text": "absent-minded which is why I have to"
        },
        {
            "start": "899.66",
            "dur": "3",
            "text": "have two people telling me every morning"
        },
        {
            "start": "901.279",
            "dur": "3.18",
            "text": "what I'm doing that day and that does"
        },
        {
            "start": "902.66",
            "dur": "3.09",
            "text": "not include my wife we didn't really"
        },
        {
            "start": "904.459",
            "dur": "2.73",
            "text": "have to build a company you tell me what"
        },
        {
            "start": "905.75",
            "dur": "3.389",
            "text": "my schedule is every day because I'm so"
        },
        {
            "start": "907.189",
            "dur": "5.221",
            "text": "absent-minded I lose my wallet phone and"
        },
        {
            "start": "909.139",
            "dur": "4.56",
            "text": "keys all the time and it was time you"
        },
        {
            "start": "912.41",
            "dur": "2.429",
            "text": "get frustrated my wife also has a"
        },
        {
            "start": "913.699",
            "dur": "3.211",
            "text": "tendency to do that so we stare at each"
        },
        {
            "start": "914.839",
            "dur": "3.391",
            "text": "other in annoyance on a frequent basis"
        },
        {
            "start": "916.91",
            "dur": "2.64",
            "text": "wondering where we put our stuff and"
        },
        {
            "start": "918.23",
            "dur": "3.75",
            "text": "that's why our marriage has been"
        },
        {
            "start": "919.55",
            "dur": "4.05",
            "text": "improved dramatically by the"
        },
        {
            "start": "921.98",
            "dur": "2.88",
            "text": "by traveler trackers just great what you"
        },
        {
            "start": "923.6",
            "dur": "2.58",
            "text": "do is you take this tracker device like"
        },
        {
            "start": "924.86",
            "dur": "3.21",
            "text": "a coin size device you stick it on your"
        },
        {
            "start": "926.18",
            "dur": "3.12",
            "text": "keychain and then it connects to your"
        },
        {
            "start": "928.07",
            "dur": "2.88",
            "text": "phone with a program and you can hit"
        },
        {
            "start": "929.3",
            "dur": "2.88",
            "text": "this button on your phone and now your"
        },
        {
            "start": "930.95",
            "dur": "3.63",
            "text": "keys will start beeping and you can find"
        },
        {
            "start": "932.18",
            "dur": "3.69",
            "text": "your keys or if you lose your phone then"
        },
        {
            "start": "934.58",
            "dur": "2.46",
            "text": "you can actually hit the thing on your"
        },
        {
            "start": "935.87",
            "dur": "2.07",
            "text": "keys and that will link to your phone"
        },
        {
            "start": "937.04",
            "dur": "2.4",
            "text": "and even if your phone is on silent"
        },
        {
            "start": "937.94",
            "dur": "2.82",
            "text": "right the tap install the time you lose"
        },
        {
            "start": "939.44",
            "dur": "3.3",
            "text": "your phone it's on silent you can't find"
        },
        {
            "start": "940.76",
            "dur": "3.3",
            "text": "it instead it now rings through so"
        },
        {
            "start": "942.74",
            "dur": "2.67",
            "text": "you'll never lose your wallet or your"
        },
        {
            "start": "944.06",
            "dur": "2.37",
            "text": "phone or your keys again your marriage"
        },
        {
            "start": "945.41",
            "dur": "3.33",
            "text": "will be better you will become a better"
        },
        {
            "start": "946.43",
            "dur": "3.66",
            "text": "person I promise that your marriage will"
        },
        {
            "start": "948.74",
            "dur": "2.52",
            "text": "if you're on the verge of divorce now"
        },
        {
            "start": "950.09",
            "dur": "2.97",
            "text": "you'll have the most glorious marriage"
        },
        {
            "start": "951.26",
            "dur": "3.51",
            "text": "that ever was thanks to tracker because"
        },
        {
            "start": "953.06",
            "dur": "3.39",
            "text": "that's just what they do you're never"
        },
        {
            "start": "954.77",
            "dur": "3.54",
            "text": "going to lose this stuff again tracker"
        },
        {
            "start": "956.45",
            "dur": "3.33",
            "text": "changes everything so they have"
        },
        {
            "start": "958.31",
            "dur": "3.63",
            "text": "something new that's called the tracker"
        },
        {
            "start": "959.78",
            "dur": "3.51",
            "text": "pixel and the tracker pixels lettuce"
        },
        {
            "start": "961.94",
            "dur": "4.29",
            "text": "Bluetooth tracking device on the market"
        },
        {
            "start": "963.29",
            "dur": "4.29",
            "text": "again put it on everything and it'll we"
        },
        {
            "start": "966.23",
            "dur": "1.74",
            "text": "put it on our baby so that we don't lose"
        },
        {
            "start": "967.58",
            "dur": "2.49",
            "text": "the baby"
        },
        {
            "start": "967.97",
            "dur": "3.78",
            "text": "and you'll never lose anything again"
        },
        {
            "start": "970.07",
            "dur": "3.03",
            "text": "right now you can get the third they"
        },
        {
            "start": "971.75",
            "dur": "5.16",
            "text": "also have a 30-day money-back guarantee"
        },
        {
            "start": "973.1",
            "dur": "6.6",
            "text": "go to tracker comments TR ACK are calm"
        },
        {
            "start": "976.91",
            "dur": "4.53",
            "text": "the tracker calm and for that promo code"
        },
        {
            "start": "979.7",
            "dur": "4.62",
            "text": "Ben you get 20% off any order you choose"
        },
        {
            "start": "981.44",
            "dur": "6.99",
            "text": "that the tracker comm promo code Ben for"
        },
        {
            "start": "984.32",
            "dur": "6.21",
            "text": "20% off the tracker comm promo code Ben"
        },
        {
            "start": "988.43",
            "dur": "3.93",
            "text": "and you're never going to lose anything"
        },
        {
            "start": "990.53",
            "dur": "3.06",
            "text": "again which for me is an important thing"
        },
        {
            "start": "992.36",
            "dur": "3.93",
            "text": "and I think it will be for you as well"
        },
        {
            "start": "993.59",
            "dur": "4.83",
            "text": "okay so we are we're through three of"
        },
        {
            "start": "996.29",
            "dur": "5.94",
            "text": "the four steps in cnn's total self"
        },
        {
            "start": "998.42",
            "dur": "5.82",
            "text": "macleod i mean at this point the only"
        },
        {
            "start": "1002.23",
            "dur": "3.42",
            "text": "way to describe this is that they"
        },
        {
            "start": "1004.24",
            "dur": "3.81",
            "text": "deliberately decided to kick themselves"
        },
        {
            "start": "1005.65",
            "dur": "3.84",
            "text": "in the groin as hard as humanly possible"
        },
        {
            "start": "1008.05",
            "dur": "3.54",
            "text": "and now all their appendages are out of"
        },
        {
            "start": "1009.49",
            "dur": "5.19",
            "text": "order because it just continues okay so"
        },
        {
            "start": "1011.59",
            "dur": "4.8",
            "text": "here's where it goes from here now CNN"
        },
        {
            "start": "1014.68",
            "dur": "2.91",
            "text": "defends itself from the blackmail"
        },
        {
            "start": "1016.39",
            "dur": "3.12",
            "text": "accusations he no no no we never"
        },
        {
            "start": "1017.59",
            "dur": "3.36",
            "text": "blackmailed anyone he said we decided"
        },
        {
            "start": "1019.51",
            "dur": "2.78",
            "text": "not to publish the name of the reddit"
        },
        {
            "start": "1020.95",
            "dur": "3.81",
            "text": "user out of concern for his safety"
        },
        {
            "start": "1022.29",
            "dur": "4.27",
            "text": "here's the problem you also threatened"
        },
        {
            "start": "1024.76",
            "dur": "4.949",
            "text": "to release his name if he changed his"
        },
        {
            "start": "1026.56",
            "dur": "5.639",
            "text": "behavior so where is the safety threat"
        },
        {
            "start": "1029.709",
            "dur": "4.141",
            "text": "coming from now CNN it's coming from you"
        },
        {
            "start": "1032.199",
            "dur": "3.691",
            "text": "because you're threatening to release"
        },
        {
            "start": "1033.85",
            "dur": "3.599",
            "text": "his name if he doesn't obey you but"
        },
        {
            "start": "1035.89",
            "dur": "3.9",
            "text": "that's not the bad part okay that's not"
        },
        {
            "start": "1037.449",
            "dur": "4.681",
            "text": "the bad part here is the worst part they"
        },
        {
            "start": "1039.79",
            "dur": "3.83",
            "text": "got the wrong guy okay they got the"
        },
        {
            "start": "1042.13",
            "dur": "4.65",
            "text": "wrong guy to try it they tracked down"
        },
        {
            "start": "1043.62",
            "dur": "6.49",
            "text": "Rebel Alliance hero Han a whole solo"
        },
        {
            "start": "1046.78",
            "dur": "5.34",
            "text": "they tracked him down on planet Endor"
        },
        {
            "start": "1050.11",
            "dur": "3.99",
            "text": "and then they failed to get the right"
        },
        {
            "start": "1052.12",
            "dur": "3.419",
            "text": "guy they got the wrong guy the BuzzFeed"
        },
        {
            "start": "1054.1",
            "dur": "3.75",
            "text": "here's BuzzFeed reporting"
        },
        {
            "start": "1055.539",
            "dur": "4.83",
            "text": "this is amazing according to BuzzFeed"
        },
        {
            "start": "1057.85",
            "dur": "4.47",
            "text": "quote one user pointed out that what"
        },
        {
            "start": "1060.369",
            "dur": "2.821",
            "text": "Trump tweeted wasn't actually Han a-hole"
        },
        {
            "start": "1062.32",
            "dur": "2.609",
            "text": "solos gift"
        },
        {
            "start": "1063.19",
            "dur": "3.539",
            "text": "Trump's gift included both video and"
        },
        {
            "start": "1064.929",
            "dur": "3.38",
            "text": "audio whereas the rebel smuggled"
        },
        {
            "start": "1066.729",
            "dur": "3.721",
            "text": "wannabes gift did not include audio"
        },
        {
            "start": "1068.309",
            "dur": "3.82",
            "text": "furthermore the original Han a whole"
        },
        {
            "start": "1070.45",
            "dur": "4.319",
            "text": "solo gift was shorter had a different"
        },
        {
            "start": "1072.129",
            "dur": "4.53",
            "text": "aspect ratio and had a WWE logo in the"
        },
        {
            "start": "1074.769",
            "dur": "2.76",
            "text": "corner not even the colors are processed"
        },
        {
            "start": "1076.659",
            "dur": "4.02",
            "text": "in the same manner"
        },
        {
            "start": "1077.529",
            "dur": "5.551",
            "text": "han Solo honeyhole solos gift has an"
        },
        {
            "start": "1080.679",
            "dur": "3.781",
            "text": "NTSC aspect ratio because it was cut"
        },
        {
            "start": "1083.08",
            "dur": "3.179",
            "text": "directly from the taping of an analogue"
        },
        {
            "start": "1084.46",
            "dur": "4.26",
            "text": "West at WrestleMania footage Trump's"
        },
        {
            "start": "1086.259",
            "dur": "4.77",
            "text": "video has an aspect ratio of 16 to 9 and"
        },
        {
            "start": "1088.72",
            "dur": "3.99",
            "text": "it continues someone downloaded the gift"
        },
        {
            "start": "1091.029",
            "dur": "3.48",
            "text": "that Han a whole solo originally posted"
        },
        {
            "start": "1092.71",
            "dur": "3.329",
            "text": "to Reddit the person cropped it to"
        },
        {
            "start": "1094.509",
            "dur": "2.85",
            "text": "better fit a video player like Facebook"
        },
        {
            "start": "1096.039",
            "dur": "2.73",
            "text": "or YouTube they went through the effort"
        },
        {
            "start": "1097.359",
            "dur": "3.361",
            "text": "of syncing it back up with the audio"
        },
        {
            "start": "1098.769",
            "dur": "3.451",
            "text": "from the original clip then they put it"
        },
        {
            "start": "1100.72",
            "dur": "2.519",
            "text": "where Trump or one of trumps people"
        },
        {
            "start": "1102.22",
            "dur": "2.519",
            "text": "could see it and download it so in other"
        },
        {
            "start": "1103.239",
            "dur": "3.78",
            "text": "words something you can get it from"
        },
        {
            "start": "1104.739",
            "dur": "4.351",
            "text": "reddit ok Trump got it from Facebook"
        },
        {
            "start": "1107.019",
            "dur": "4.11",
            "text": "Trump got it from Facebook or from"
        },
        {
            "start": "1109.09",
            "dur": "4.11",
            "text": "YouTube and then you put it up so their"
        },
        {
            "start": "1111.129",
            "dur": "3.93",
            "text": "friends link this guy who made it on"
        },
        {
            "start": "1113.2",
            "dur": "2.76",
            "text": "reddit who's not linked to Trump in any"
        },
        {
            "start": "1115.059",
            "dur": "2.43",
            "text": "way they're trying to link to the"
        },
        {
            "start": "1115.96",
            "dur": "3.809",
            "text": "ancillary stuff that Trump has never"
        },
        {
            "start": "1117.489",
            "dur": "4.951",
            "text": "seen to Trump in order to call Trump a"
        },
        {
            "start": "1119.769",
            "dur": "3.84",
            "text": "racist anti-semite and then they got and"
        },
        {
            "start": "1122.44",
            "dur": "2.549",
            "text": "then they're threatening the guy and"
        },
        {
            "start": "1123.609",
            "dur": "5.76",
            "text": "they got the wrong guy"
        },
        {
            "start": "1124.989",
            "dur": "6.24",
            "text": "come here no this is just it's sheer"
        },
        {
            "start": "1129.369",
            "dur": "3.51",
            "text": "incompetence of the highest order and"
        },
        {
            "start": "1131.229",
            "dur": "2.82",
            "text": "all this does of course is it helps"
        },
        {
            "start": "1132.879",
            "dur": "2.43",
            "text": "Trump but I mean Trump is just sitting"
        },
        {
            "start": "1134.049",
            "dur": "2.94",
            "text": "there going I've been calling them"
        },
        {
            "start": "1135.309",
            "dur": "2.881",
            "text": "taking use all the time should I say the"
        },
        {
            "start": "1136.989",
            "dur": "2.28",
            "text": "fake news even when the reporting we do"
        },
        {
            "start": "1138.19",
            "dur": "3.719",
            "text": "stuff but now they're big news all the"
        },
        {
            "start": "1139.269",
            "dur": "4.23",
            "text": "time it's just like could he have paid"
        },
        {
            "start": "1141.909",
            "dur": "3.96",
            "text": "them like Trump doesn't even have to buy"
        },
        {
            "start": "1143.499",
            "dur": "3.81",
            "text": "them because he now owns them right or"
        },
        {
            "start": "1145.869",
            "dur": "3.571",
            "text": "if he doesn't own them they self owned I"
        },
        {
            "start": "1147.309",
            "dur": "4.771",
            "text": "mean it's just it's unbelievable it's"
        },
        {
            "start": "1149.44",
            "dur": "4.679",
            "text": "just incredible and that wasn't by the"
        },
        {
            "start": "1152.08",
            "dur": "5.399",
            "text": "way even that is not the end of the"
        },
        {
            "start": "1154.119",
            "dur": "5.73",
            "text": "story because yesterday CNN 2 times 2"
        },
        {
            "start": "1157.479",
            "dur": "4.02",
            "text": "times apparently had fake quotes one"
        },
        {
            "start": "1159.849",
            "dur": "3.241",
            "text": "from Abraham Lincoln you know dumb you"
        },
        {
            "start": "1161.499",
            "dur": "3.6",
            "text": "have to be to run a story that is a fake"
        },
        {
            "start": "1163.09",
            "dur": "3.569",
            "text": "quote from Abraham Lincoln kiss on she's"
        },
        {
            "start": "1165.099",
            "dur": "2.851",
            "text": "making new stuff up every day Abraham"
        },
        {
            "start": "1166.659",
            "dur": "3.39",
            "text": "Lincoln tonight he's coming out with new"
        },
        {
            "start": "1167.95",
            "dur": "3.419",
            "text": "material that you have to bet isn't dead"
        },
        {
            "start": "1170.049",
            "dur": "3.06",
            "text": "for 150 years"
        },
        {
            "start": "1171.369",
            "dur": "3.211",
            "text": "I mean president from may not know that"
        },
        {
            "start": "1173.109",
            "dur": "3.06",
            "text": "he thinks Andrew Jackson still alive and"
        },
        {
            "start": "1174.58",
            "dur": "3.899",
            "text": "so Frederick Douglass but but the fact"
        },
        {
            "start": "1176.169",
            "dur": "4.291",
            "text": "is that Abraham Lincoln I think Trump is"
        },
        {
            "start": "1178.479",
            "dur": "3.3",
            "text": "aware that he's dead and certainly CNN"
        },
        {
            "start": "1180.46",
            "dur": "3.63",
            "text": "should be I mean no the one saying Trump"
        },
        {
            "start": "1181.779",
            "dur": "3.691",
            "text": "is so stupid he so don't quote Abraham"
        },
        {
            "start": "1184.09",
            "dur": "2.789",
            "text": "Lincoln when he's not saying news that"
        },
        {
            "start": "1185.47",
            "dur": "3.87",
            "text": "it's just it's unbelievable"
        },
        {
            "start": "1186.879",
            "dur": "2.67",
            "text": "and then everyone wonders why trust in"
        },
        {
            "start": "1189.34",
            "dur": "2.73",
            "text": "the"
        },
        {
            "start": "1189.549",
            "dur": "5.401",
            "text": "maybe declining I can't imagine why"
        },
        {
            "start": "1192.07",
            "dur": "4.679",
            "text": "trust in the media is declining so when"
        },
        {
            "start": "1194.95",
            "dur": "4.14",
            "text": "we continue on the other side here I"
        },
        {
            "start": "1196.749",
            "dur": "3.75",
            "text": "want to talk about some Republican"
        },
        {
            "start": "1199.09",
            "dur": "3.209",
            "text": "silliness that happened over the weekend"
        },
        {
            "start": "1200.499",
            "dur": "5.04",
            "text": "also on the media because we can't just"
        },
        {
            "start": "1202.299",
            "dur": "4.5",
            "text": "have Republicans have gone we've gotten"
        },
        {
            "start": "1205.539",
            "dur": "2.551",
            "text": "the point where the tensions be partisan"
        },
        {
            "start": "1206.799",
            "dur": "3.09",
            "text": "silliness there have to be bipartisan"
        },
        {
            "start": "1208.09",
            "dur": "3.6",
            "text": "silliness like everyone has to drink the"
        },
        {
            "start": "1209.889",
            "dur": "3.42",
            "text": "kuku juice and now everyone has lost"
        },
        {
            "start": "1211.69",
            "dur": "4.14",
            "text": "their minds so we'll get to more"
        },
        {
            "start": "1213.309",
            "dur": "3.45",
            "text": "insanity July 4th insanity but first"
        },
        {
            "start": "1215.83",
            "dur": "2.309",
            "text": "you're going to have to go over to Daily"
        },
        {
            "start": "1216.759",
            "dur": "2.821",
            "text": "wire and subscribe so for eight dollars"
        },
        {
            "start": "1218.139",
            "dur": "3.87",
            "text": "a month you too can become a subscriber"
        },
        {
            "start": "1219.58",
            "dur": "3.689",
            "text": "to daily wired.com that gets you the"
        },
        {
            "start": "1222.009",
            "dur": "2.55",
            "text": "rest of the show live against you the"
        },
        {
            "start": "1223.269",
            "dur": "3.12",
            "text": "mailbag which we're doing on Friday"
        },
        {
            "start": "1224.559",
            "dur": "2.881",
            "text": "if you enter Clayton's show live as well"
        },
        {
            "start": "1226.389",
            "dur": "3",
            "text": "as the mailbag we're launching some"
        },
        {
            "start": "1227.44",
            "dur": "3.299",
            "text": "other shows too plus you get the ad free"
        },
        {
            "start": "1229.389",
            "dur": "3.451",
            "text": "experience on the website which is"
        },
        {
            "start": "1230.739",
            "dur": "3.27",
            "text": "awesome and you get all that for just"
        },
        {
            "start": "1232.84",
            "dur": "2.669",
            "text": "eight dollars a month make sure you lock"
        },
        {
            "start": "1234.009",
            "dur": "3.15",
            "text": "in your subscription now because our"
        },
        {
            "start": "1235.509",
            "dur": "2.971",
            "text": "rates are going up on July 10 if you"
        },
        {
            "start": "1237.159",
            "dur": "2.911",
            "text": "want the annual subscription you get a"
        },
        {
            "start": "1238.48",
            "dur": "3.48",
            "text": "free signed copy of the book I wrote"
        },
        {
            "start": "1240.07",
            "dur": "4.349",
            "text": "with my dad's say it's so about baseball"
        },
        {
            "start": "1241.96",
            "dur": "3.99",
            "text": "and fathers and sons really fun book and"
        },
        {
            "start": "1244.419",
            "dur": "2.88",
            "text": "I will autograph it for you can treasure"
        },
        {
            "start": "1245.95",
            "dur": "3.419",
            "text": "it you can keep it forever handed down"
        },
        {
            "start": "1247.299",
            "dur": "3.931",
            "text": "to your grandchildren or alternatively"
        },
        {
            "start": "1249.369",
            "dur": "2.91",
            "text": "sell it on eBay for a profit I won't"
        },
        {
            "start": "1251.23",
            "dur": "2.429",
            "text": "tell you what to do with it in any case"
        },
        {
            "start": "1252.279",
            "dur": "3.39",
            "text": "you can get that for free when a Pony"
        },
        {
            "start": "1253.659",
            "dur": "4.291",
            "text": "annual subscriber or just one to listen"
        },
        {
            "start": "1255.669",
            "dur": "3.541",
            "text": "later in iTunes or SoundCloud then go"
        },
        {
            "start": "1257.95",
            "dur": "3.089",
            "text": "over there subscribe leave us a review"
        },
        {
            "start": "1259.21",
            "dur": "3.209",
            "text": "we always appreciate it make sure that"
        },
        {
            "start": "1261.039",
            "dur": "2.82",
            "text": "the way you should we've reviewed by the"
        },
        {
            "start": "1262.419",
            "dur": "3.51",
            "text": "way is however many stars you think the"
        },
        {
            "start": "1263.859",
            "dur": "3.45",
            "text": "show deserves add 5 to it and then leave"
        },
        {
            "start": "1265.929",
            "dur": "3.391",
            "text": "a review because that's the best way to"
        },
        {
            "start": "1267.309",
            "dur": "3.69",
            "text": "do it in any case you can join us on the"
        },
        {
            "start": "1269.32",
            "dur": "3",
            "text": "other side when you subscribe we are the"
        },
        {
            "start": "1270.999",
            "dur": "2.091",
            "text": "largest conservative podcast in the"
        },
        {
            "start": "1272.32",
            "dur": "6.16",
            "text": "nation"
        },
        {
            "start": "1273.09",
            "dur": "7.45",
            "text": "[Music]"
        },
        {
            "start": "1278.48",
            "dur": "2.06",
            "text": "you"
        }
    ]
}